kegg_cli/__about__.py
kegg_cli/__init__.py
kegg_cli/_utils.py
kegg_cli/arg_enums.py
kegg_cli/conventional_cmds.py
kegg_cli/get_seq.py
kegg_cli/kegg_conv.py
kegg_cli/main.py
kegg_cli-0.0.1.dist-info/METADATA
kegg_cli-0.0.1.dist-info/WHEEL
kegg_cli-0.0.1.dist-info/entry_points.txt
kegg_cli-0.0.1.dist-info/licenses/LICENSE.txt
kegg_cli-0.0.1.dist-info/RECORD
