Metadata-Version: 2.4
Name: kegg-cli
Version: 0.0.1
Summary: a CLI tool for KEGG. It can use all conventional KEGG REST API commands and a custom command get-seq to get nt/aa seq from given gene IDs/pathway/module
Project-URL: Documentation, https://github.com/vidyasagar0405/kegg-cli#readme
Project-URL: Issues, https://github.com/vidyasagar0405/kegg-cli/issues
Project-URL: Source, https://github.com/vidyasagar0405/kegg-cli
Author-email: vidyasagar0405 <vidyasagar0405@gmail.com>
License-Expression: MIT
License-File: LICENSE.txt
Keywords: KEGG,cli
Classifier: Development Status :: 4 - Beta
Classifier: Programming Language :: Python
Classifier: Programming Language :: Python :: 3.8
Classifier: Programming Language :: Python :: 3.9
Classifier: Programming Language :: Python :: 3.10
Classifier: Programming Language :: Python :: 3.11
Classifier: Programming Language :: Python :: 3.12
Classifier: Programming Language :: Python :: Implementation :: CPython
Classifier: Programming Language :: Python :: Implementation :: PyPy
Requires-Python: >=3.8
Requires-Dist: biopython
Requires-Dist: rich
Requires-Dist: typer
